docs/default.primers
ribdif/__init__.py
ribdif/__main__.py
ribdif/barrnap_run.py
ribdif/correcting_tools.py
ribdif/make_heatmap.py
ribdif/msa_run.py
ribdif/ngd_download.py
ribdif/overlaps.py
ribdif/pcr_run.py
ribdif/pyani_run.py
ribdif/summary_16S.py
ribdif/utils.py
ribdif/vsearch_run.py
ribdif-1.1.3.dist-info/METADATA
ribdif-1.1.3.dist-info/WHEEL
ribdif-1.1.3.dist-info/entry_points.txt
ribdif-1.1.3.dist-info/licenses/LICENSE
ribdif-1.1.3.dist-info/RECORD
